cashlog/__init__.py
cashlog/__main__.py
cashlog/cli.py
cashlog-1.0.0.dist-info/LICENSE
cashlog-1.0.0.dist-info/METADATA
cashlog-1.0.0.dist-info/WHEEL
cashlog-1.0.0.dist-info/entry_points.txt
cashlog-1.0.0.dist-info/top_level.txt
cashlog-1.0.0.dist-info/RECORD
