Metadata-Version: 2.1
Name: cashlog
Version: 1.0.0
Summary: Cash flow tracker
Home-page: https://github.com/dmotte/cashlog
Author: dmotte
License: MIT
Keywords: calculator csv command value cumulative cashlog tracker flow money tracking finance statistics monitor monitoring log analysis management cash track budgeting budget
Classifier: Intended Audience :: End Users/Desktop
Classifier: Environment :: Console
Classifier: Natural Language :: English
Classifier: License :: OSI Approved :: MIT License
Classifier: Programming Language :: Python
Classifier: Programming Language :: Python :: 3
Classifier: Programming Language :: Python :: 3 :: Only
Classifier: Programming Language :: Python :: 3.10
Classifier: Topic :: Terminals
Classifier: Topic :: Utilities
Requires-Python: >=3.10.12
License-File: LICENSE
Requires-Dist: python-dateutil<2.10,>=2.9.0
